{
	"configurations" : 
	[
		{
			"directories" : 
			[
				{
					"build" : ".",
					"childIndexes" : 
					[
						1,
						2,
						6
					],
					"hasInstallRule" : true,
					"jsonFile" : "directory-.-Debug-f5ebdc15457944623624.json",
					"minimumCMakeVersion" : 
					{
						"string" : "3.20"
					},
					"projectIndex" : 0,
					"source" : "."
				},
				{
					"build" : "_deps/fmt-build",
					"hasInstallRule" : true,
					"jsonFile" : "directory-_deps.fmt-build-Debug-5fdc658439673d16a1bc.json",
					"minimumCMakeVersion" : 
					{
						"string" : "3.8"
					},
					"parentIndex" : 0,
					"projectIndex" : 1,
					"source" : "cmake-build-debug/_deps/fmt-src",
					"targetIndexes" : 
					[
						1
					]
				},
				{
					"build" : "src",
					"childIndexes" : 
					[
						3,
						4,
						5
					],
					"jsonFile" : "directory-src-Debug-b6cf2213fc5053b67c22.json",
					"minimumCMakeVersion" : 
					{
						"string" : "3.20"
					},
					"parentIndex" : 0,
					"projectIndex" : 0,
					"source" : "src",
					"targetIndexes" : 
					[
						0
					]
				},
				{
					"build" : "src/matching_engine",
					"jsonFile" : "directory-src.matching_engine-Debug-c5b3ac1f21b1f7a5be06.json",
					"minimumCMakeVersion" : 
					{
						"string" : "3.20"
					},
					"parentIndex" : 2,
					"projectIndex" : 0,
					"source" : "src/matching_engine",
					"targetIndexes" : 
					[
						7
					]
				},
				{
					"build" : "src/order_manager",
					"jsonFile" : "directory-src.order_manager-Debug-b48b13b4dec83d8ec92b.json",
					"minimumCMakeVersion" : 
					{
						"string" : "3.20"
					},
					"parentIndex" : 2,
					"projectIndex" : 0,
					"source" : "src/order_manager",
					"targetIndexes" : 
					[
						8
					]
				},
				{
					"build" : "src/market_data",
					"jsonFile" : "directory-src.market_data-Debug-2edb7e5bf795c5e0bc74.json",
					"minimumCMakeVersion" : 
					{
						"string" : "3.20"
					},
					"parentIndex" : 2,
					"projectIndex" : 0,
					"source" : "src/market_data",
					"targetIndexes" : 
					[
						6
					]
				},
				{
					"build" : "tests",
					"childIndexes" : 
					[
						7
					],
					"hasInstallRule" : true,
					"jsonFile" : "directory-tests-Debug-b01f6abb0ab61427ef3b.json",
					"minimumCMakeVersion" : 
					{
						"string" : "3.20"
					},
					"parentIndex" : 0,
					"projectIndex" : 0,
					"source" : "tests",
					"targetIndexes" : 
					[
						9
					]
				},
				{
					"build" : "_deps/googletest-build",
					"childIndexes" : 
					[
						8
					],
					"hasInstallRule" : true,
					"jsonFile" : "directory-_deps.googletest-build-Debug-fa1b18db30f420365ea4.json",
					"minimumCMakeVersion" : 
					{
						"string" : "3.5"
					},
					"parentIndex" : 6,
					"projectIndex" : 2,
					"source" : "cmake-build-debug/_deps/googletest-src"
				},
				{
					"build" : "_deps/googletest-build/googlemock",
					"childIndexes" : 
					[
						9
					],
					"hasInstallRule" : true,
					"jsonFile" : "directory-_deps.googletest-build.googlemock-Debug-97eb8eab7e56a33455a7.json",
					"minimumCMakeVersion" : 
					{
						"string" : "3.5"
					},
					"parentIndex" : 7,
					"projectIndex" : 3,
					"source" : "cmake-build-debug/_deps/googletest-src/googlemock",
					"targetIndexes" : 
					[
						2,
						3
					]
				},
				{
					"build" : "_deps/googletest-build/googletest",
					"hasInstallRule" : true,
					"jsonFile" : "directory-_deps.googletest-build.googletest-Debug-68c9c31aba8510311e53.json",
					"minimumCMakeVersion" : 
					{
						"string" : "3.5"
					},
					"parentIndex" : 8,
					"projectIndex" : 4,
					"source" : "cmake-build-debug/_deps/googletest-src/googletest",
					"targetIndexes" : 
					[
						4,
						5
					]
				}
			],
			"name" : "Debug",
			"projects" : 
			[
				{
					"childIndexes" : 
					[
						1,
						2
					],
					"directoryIndexes" : 
					[
						0,
						2,
						3,
						4,
						5,
						6
					],
					"name" : "CryptoExchange",
					"targetIndexes" : 
					[
						0,
						6,
						7,
						8,
						9
					]
				},
				{
					"directoryIndexes" : 
					[
						1
					],
					"name" : "FMT",
					"parentIndex" : 0,
					"targetIndexes" : 
					[
						1
					]
				},
				{
					"childIndexes" : 
					[
						3
					],
					"directoryIndexes" : 
					[
						7
					],
					"name" : "googletest-distribution",
					"parentIndex" : 0
				},
				{
					"childIndexes" : 
					[
						4
					],
					"directoryIndexes" : 
					[
						8
					],
					"name" : "gmock",
					"parentIndex" : 2,
					"targetIndexes" : 
					[
						2,
						3
					]
				},
				{
					"directoryIndexes" : 
					[
						9
					],
					"name" : "gtest",
					"parentIndex" : 3,
					"targetIndexes" : 
					[
						4,
						5
					]
				}
			],
			"targets" : 
			[
				{
					"directoryIndex" : 2,
					"id" : "CryptoExchange::@145eef247bfb46b6828c",
					"jsonFile" : "target-CryptoExchange-Debug-006189ea51d3f6c68d8b.json",
					"name" : "CryptoExchange",
					"projectIndex" : 0
				},
				{
					"directoryIndex" : 1,
					"id" : "fmt::@976f4f0bee90b99ecdb6",
					"jsonFile" : "target-fmt-Debug-564b5882ff3ff82750ab.json",
					"name" : "fmt",
					"projectIndex" : 1
				},
				{
					"directoryIndex" : 8,
					"id" : "gmock::@0f7bb11d64f3678238c7",
					"jsonFile" : "target-gmock-Debug-5cba5140fa8ded7aa194.json",
					"name" : "gmock",
					"projectIndex" : 3
				},
				{
					"directoryIndex" : 8,
					"id" : "gmock_main::@0f7bb11d64f3678238c7",
					"jsonFile" : "target-gmock_main-Debug-cf1cc822a89fabe73cb5.json",
					"name" : "gmock_main",
					"projectIndex" : 3
				},
				{
					"directoryIndex" : 9,
					"id" : "gtest::@1ea2dfc0605fe3ab2a3f",
					"jsonFile" : "target-gtest-Debug-5e313745d7ee045452c5.json",
					"name" : "gtest",
					"projectIndex" : 4
				},
				{
					"directoryIndex" : 9,
					"id" : "gtest_main::@1ea2dfc0605fe3ab2a3f",
					"jsonFile" : "target-gtest_main-Debug-044d5ca304fe284c3ce5.json",
					"name" : "gtest_main",
					"projectIndex" : 4
				},
				{
					"directoryIndex" : 5,
					"id" : "market_data::@b817a725bf5f5986f9f6",
					"jsonFile" : "target-market_data-Debug-c4e502bc3a2a42155b45.json",
					"name" : "market_data",
					"projectIndex" : 0
				},
				{
					"directoryIndex" : 3,
					"id" : "matching_engine::@a901eb2aa91bb3c117a6",
					"jsonFile" : "target-matching_engine-Debug-21f367621177823c11fa.json",
					"name" : "matching_engine",
					"projectIndex" : 0
				},
				{
					"directoryIndex" : 4,
					"id" : "order_manager::@bc06ef6ad9df81cc8f96",
					"jsonFile" : "target-order_manager-Debug-ca5a0c3516c2d22c4217.json",
					"name" : "order_manager",
					"projectIndex" : 0
				},
				{
					"directoryIndex" : 6,
					"id" : "tests::@a44f0ac069e85531cdee",
					"jsonFile" : "target-tests-Debug-07a000a734ea238310dc.json",
					"name" : "tests",
					"projectIndex" : 0
				}
			]
		}
	],
	"kind" : "codemodel",
	"paths" : 
	{
		"build" : "/Users/muhammadchandrazulfikar/Documents/cpp-playground/crypto-exchange/cmake-build-debug",
		"source" : "/Users/muhammadchandrazulfikar/Documents/cpp-playground/crypto-exchange"
	},
	"version" : 
	{
		"major" : 2,
		"minor" : 7
	}
}
